selmr-0.4.2.dist-info/METADATA
selmr-0.4.2.dist-info/WHEEL
selmr/__init__.py
selmr/selmr.pyd
selmr-0.4.2.dist-info/RECORD
