Metadata-Version: 2.3
Name: selmr
Version: 0.4.2
Classifier: Programming Language :: Rust
Classifier: Programming Language :: Python :: Implementation :: CPython
Classifier: Programming Language :: Python :: Implementation :: PyPy
Summary: Package to create and use Simple Explainable Language Multiset Representations
Home-Page: https://github.com/wjwillemse/selmr
License: MIT
Requires-Python: >=3.8
Project-URL: Source Code, https://github.com/wjwillemse/selmr
